setup.py
simple_cluster/__init__.py
simple_cluster/base_cluster.py
simple_cluster/k_means.py
simple_cluster/k_means_plus.py
simply_cluster.egg-info/PKG-INFO
simply_cluster.egg-info/SOURCES.txt
simply_cluster.egg-info/dependency_links.txt
simply_cluster.egg-info/not-zip-safe
simply_cluster.egg-info/top_level.txt