Metadata-Version: 1.0
Name: simply-cluster
Version: 1.0
Summary: A simply realisation of k-means and k-means++
Home-page: UNKNOWN
Author: Lujing Yang
Author-email: lujing@me.com
License: UNKNOWN
Platform: UNKNOWN
